libemtk/__init__.py
libemtk/clusters/__init__.py
libemtk/clusters/cluster_trait.py
libemtk/clusters/clusters_layer.py
libemtk/clusters/default_modifier_cluster.py
libemtk/clusters/modifiers_cluster.py
libemtk/controller/__init__.py
libemtk/controller/actions.py
libemtk/controller/answers.py
libemtk/controller/clusters_controller.py
libemtk/dummy_modifiers.py
libemtk/lists/__init__.py
libemtk/lists/extended_modifiers_list.py
libemtk/lists/modifiers_list.py
libemtk/lists/selection.py
libemtk/lists/traits/__init__.py
libemtk/lists/traits/clusters/__init__.py
libemtk/lists/traits/clusters/active_cluster.py
libemtk/lists/traits/clusters/clusters_list.py
libemtk/lists/traits/clusters/sortable_clusters_list.py
libemtk/lists/utils.py
libemtk/modifiers_operator.py
libemtk/object_state.py
libemtk/parser/__init__.py
libemtk/parser/parser_object.py
libemtk/parser/reparser_config.py
libemtk/sorting_rule.py
libemtk/utils/__init__.py
libemtk/utils/clusters.py
libemtk/utils/modifier_prop_types.py
libemtk/utils/modifiers.py
libemtk-0.1.2.dist-info/LICENSE
libemtk-0.1.2.dist-info/WHEEL
libemtk-0.1.2.dist-info/METADATA
libemtk-0.1.2.dist-info/RECORD
