Metadata-Version: 2.1
Name: libemtk
Version: 0.1.2
Summary: Extended Modifiers Tool Kit (library)
Home-page: https://github.com/0djentd/libemtk
License: GPL-3.0-or-later
Author: 0djentd
Requires-Python: >=3.9,<4.0
Classifier: License :: OSI Approved :: GNU General Public License v3 or later (GPLv3+)
Classifier: Programming Language :: Python :: 3
Classifier: Programming Language :: Python :: 3.10
Classifier: Programming Language :: Python :: 3.9
Project-URL: Repository, https://github.com/0djentd/libemtk
